browser.py
omnimd_browser_reader-0.1.3.dist-info/METADATA
omnimd_browser_reader-0.1.3.dist-info/WHEEL
omnimd_browser_reader-0.1.3.dist-info/entry_points.txt
omnimd_browser_reader-0.1.3.dist-info/RECORD
