Metadata-Version: 2.4
Name: omnimd-browser-reader
Version: 0.1.3
Summary: A plugin for omni-article-markdown to read content that needs enabling javascript.
Project-URL: Homepage, https://github.com/caol64/omni-article-markdown/tree/main/plugins/omnimd-browser-reader
Author-email: Lei <caol64@gmail.com>
License-Expression: MIT
Requires-Python: >=3.13
Requires-Dist: playwright==1.57.0
